pyFixedFlatFile/__init__.py
pyFixedFlatFile/exceptions.py
pyFixedFlatFile/pyFixedFlatFile.py
pyFixedFlatFile/specs.py
pyFixedFlatFile/cnabs/__init__.py
pyFixedFlatFile/cnabs/bradesco.py
pyFixedFlatFile/cnabs/itau.py
pyFixedFlatFile/cnabs/santander.py
pyFixedFlatFile-1.4.0.dist-info/LICENSE.txt
pyFixedFlatFile-1.4.0.dist-info/WHEEL
pyFixedFlatFile-1.4.0.dist-info/METADATA
pyFixedFlatFile-1.4.0.dist-info/RECORD
