Metadata-Version: 2.1
Name: pyFixedFlatFile
Version: 1.4.0
Summary: PyFixedFlatFile
Home-page: https://github.com/anderson89marques/PyFixedFlatFile
License: UNKNOWN
Author: Anderson Marques
Author-email: andersonoanjo18@gmail.com
Maintainer: anderson89marques
Requires-Python: >=3.5
Classifier: Programming Language :: Python :: 3.6
Classifier: Intended Audience :: Developers
Classifier: License :: OSI Approved :: MIT License
